{
  "ok": true,
  "generatedAt": "2026-06-08T18:19:20.800Z",
  "baseUrl": "http://127.0.0.1:5180",
  "results": [
    {
      "file": "reports/screenshots/learning-path-before-desktop.png",
      "path": "/learning-path",
      "viewport": {
        "width": 1440,
        "height": 950
      },
      "overflow": false
    },
    {
      "file": "reports/screenshots/learning-path-before-mobile.png",
      "path": "/learning-path",
      "viewport": {
        "width": 390,
        "height": 844
      },
      "overflow": false
    },
    {
      "file": "reports/screenshots/lesson-unit1-before-desktop.png",
      "path": "/lessons/unit-1-greetings-introduction",
      "viewport": {
        "width": 1440,
        "height": 950
      },
      "overflow": false
    },
    {
      "file": "reports/screenshots/lesson-unit1-before-mobile.png",
      "path": "/lessons/unit-1-greetings-introduction",
      "viewport": {
        "width": 390,
        "height": 844
      },
      "overflow": false
    }
  ],
  "errors": []
}